treer/__about__.py
treer/__init__.py
treer/treer.py
Treer-0.1.0.dist-info/LICENSE
Treer-0.1.0.dist-info/METADATA
Treer-0.1.0.dist-info/WHEEL
Treer-0.1.0.dist-info/top_level.txt
Treer-0.1.0.dist-info/zip-safe
Treer-0.1.0.dist-info/RECORD
