Metadata-Version: 2.1
Name: Treer
Version: 0.1.0
Summary: Ascii Tree Creator for Python!
Home-page: https://github.com/nagataaaas/Treer
Author: Yamato Nagata
Author-email: nagata@mail.nagata.pro
License: MIT
Platform: any
Classifier: Development Status :: 4 - Beta
Classifier: Environment :: Other Environment
Classifier: Intended Audience :: Developers
Classifier: License :: OSI Approved :: MIT License
Classifier: Operating System :: OS Independent
Classifier: Programming Language :: Python :: 3
Classifier: Programming Language :: Python
Classifier: Topic :: Software Development :: Libraries :: Python Modules
Classifier: Environment :: Console
License-File: LICENSE
Requires-Dist: iro (==0.8.1)
